aiorubika/__init__.py
aiorubika/client.py
aiorubika/exceptions.py
aiorubika/filters.py
aiorubika/handlers.py
aiorubika/network.py
aiorubika/utils.py
aiorubika/crypto/__init__.py
aiorubika/crypto/crypto.py
aiorubika/enums/__init__.py
aiorubika/enums/chat_access_type.py
aiorubika/enums/chat_action.py
aiorubika/enums/chat_type.py
aiorubika/enums/message_media_type.py
aiorubika/enums/poll_type.py
aiorubika/enums/reaction_type.py
aiorubika/methods/__init__.py
aiorubika/methods/advanced/__init__.py
aiorubika/methods/advanced/build.py
aiorubika/methods/auth/__init__.py
aiorubika/methods/auth/register_device.py
aiorubika/methods/auth/send_code.py
aiorubika/methods/auth/sign_in.py
aiorubika/methods/decorators/__init__.py
aiorubika/methods/decorators/on_message.py
aiorubika/methods/messages/__init__.py
aiorubika/methods/messages/send_message.py
aiorubika/methods/settings/__init__.py
aiorubika/methods/settings/get_my_sessions.py
aiorubika/methods/settings/get_two_passcode_status.py
aiorubika/methods/settings/setup_two_step_verification.py
aiorubika/methods/settings/terminate_session.py
aiorubika/methods/users/__init__.py
aiorubika/methods/users/get_me.py
aiorubika/methods/users/get_user_info.py
aiorubika/methods/utilities/__init__.py
aiorubika/methods/utilities/add_handler.py
aiorubika/methods/utilities/connect.py
aiorubika/methods/utilities/disconnect.py
aiorubika/methods/utilities/download.py
aiorubika/methods/utilities/download_profile_picture.py
aiorubika/methods/utilities/get_members.py
aiorubika/methods/utilities/get_updates.py
aiorubika/methods/utilities/remove_handler.py
aiorubika/methods/utilities/run.py
aiorubika/methods/utilities/start.py
aiorubika/methods/utilities/thumbnail.py
aiorubika/methods/utilities/upload.py
aiorubika/parser/__init__.py
aiorubika/parser/markdown.py
aiorubika/parser/parser.py
aiorubika/sessions/__init__.py
aiorubika/sessions/sqlite_session.py
aiorubika/sessions/string_session.py
aiorubika/types/__init__.py
aiorubika/types/abs_object.py
aiorubika-1.0.0.dist-info/LICENSE
aiorubika-1.0.0.dist-info/METADATA
aiorubika-1.0.0.dist-info/WHEEL
aiorubika-1.0.0.dist-info/top_level.txt
aiorubika-1.0.0.dist-info/RECORD
